pysankey/__init__.py
pysankey/sankey/__init__.py
pysankey/sankey/exceptions.py
pysankeybeta-1.4.2.dist-info/LICENSE
pysankeybeta-1.4.2.dist-info/METADATA
pysankeybeta-1.4.2.dist-info/WHEEL
pysankeybeta-1.4.2.dist-info/top_level.txt
pysankeybeta-1.4.2.dist-info/RECORD
