Metadata-Version: 2.1
Name: pysankeybeta
Version: 1.4.2
Summary: Make simple, pretty Sankey Diagrams (Beta version)
Author-email: Pierre Sassoulas <pierre.sassoulas@gmail.com>
License: GNU General Public License v3.0
Project-URL: Homepage, https://github.com/pierre-sassoulas/pySankey
Classifier: License :: OSI Approved :: GNU Affero General Public License v3
Classifier: Operating System :: OS Independent
Classifier: Programming Language :: Python :: 3 :: Only
Classifier: Programming Language :: Python :: 3.8
Classifier: Programming Language :: Python :: 3.9
Classifier: Programming Language :: Python :: 3.10
Classifier: Programming Language :: Python :: 3.11
Classifier: Programming Language :: Python :: 3.12
Requires-Python: >=3.8
License-File: LICENSE
Requires-Dist: matplotlib >=2.1.0rc1
Requires-Dist: numpy >=1.16.5
Requires-Dist: pandas
Requires-Dist: seaborn >=0.8.1
Provides-Extra: test
Requires-Dist: coverage ; extra == 'test'
Requires-Dist: coveralls ; extra == 'test'
Requires-Dist: pre-commit ; extra == 'test'
Requires-Dist: pylint <3.3,>=2.14.5 ; extra == 'test'
Requires-Dist: pytest-cov ; extra == 'test'
